netaio/__init__.py
netaio/asymmetric.py
netaio/auth.py
netaio/cipher.py
netaio/client.py
netaio/common.py
netaio/crypto.py
netaio/node.py
netaio/server.py
netaio-0.0.8.dist-info/METADATA
netaio-0.0.8.dist-info/WHEEL
netaio-0.0.8.dist-info/RECORD
