Metadata-Version: 2.4
Name: netaio
Version: 0.0.8
Summary: Simple asyncio TCP client and server and UDP node library inspired by fastapi
Project-URL: Homepage, https://github.com/k98kurz/netaio
Project-URL: Repository, https://github.com/k98kurz/netaio
Project-URL: Bug Tracker, https://github.com/k98kurz/netaio/issues
Author-email: k98kurz <k98kurz@gmail.com>
Classifier: Development Status :: 2 - Pre-Alpha
Classifier: License :: OSI Approved :: ISC License (ISCL)
Classifier: Operating System :: OS Independent
Classifier: Programming Language :: Python :: 3
Classifier: Topic :: Internet
Classifier: Topic :: Software Development :: Libraries :: Application Frameworks
Requires-Python: >=3.10
Requires-Dist: packify>=0.3.1
Provides-Extra: asymmetric
Requires-Dist: pynacl>=1.5.0; extra == 'asymmetric'
Requires-Dist: tapescript>=0.7.2; extra == 'asymmetric'
